setup.py
mlndjw_distributions/Binomialdistribution.py
mlndjw_distributions/Gaussiandistribution.py
mlndjw_distributions/Generaldistribution.py
mlndjw_distributions/__init__.py
mlndjw_distributions.egg-info/PKG-INFO
mlndjw_distributions.egg-info/SOURCES.txt
mlndjw_distributions.egg-info/dependency_links.txt
mlndjw_distributions.egg-info/not-zip-safe
mlndjw_distributions.egg-info/top_level.txt